arcoai/__init__.py
arcoai/ann.py
arcoai/backends.py
arcoai/cnn.py
arcoai/datasets.py
arcoai/hypertune.py
arcoai/training.py
arcoai/utils.py
arcoai/visualization.py
arcoai/models/__init__.py
arcoai/models/densenet.py
arcoai/models/resnet.py
arcoai/models/vgg.py
arcoai-0.1.1.dist-info/LICENSE
arcoai-0.1.1.dist-info/METADATA
arcoai-0.1.1.dist-info/WHEEL
arcoai-0.1.1.dist-info/entry_points.txt
arcoai-0.1.1.dist-info/top_level.txt
arcoai-0.1.1.dist-info/RECORD
