Metadata-Version: 2.2
Name: arcoai
Version: 0.1.1
Summary: A library for easy creation of ANN and CNN models with integrated visualization tools
Home-page: https://github.com/Arcoson/arcoai
Author: Arcoson
Author-email: hylendust@gmail.com
Classifier: Programming Language :: Python :: 3
Classifier: License :: OSI Approved :: MIT License
Classifier: Operating System :: OS Independent
Classifier: Intended Audience :: Developers
Classifier: Topic :: Software Development :: Libraries :: Python Modules
Classifier: Topic :: Scientific/Engineering :: Artificial Intelligence
Requires-Python: >=3.6
License-File: LICENSE
Requires-Dist: tensorflow>=2.0
Requires-Dist: torch>=1.7
Requires-Dist: numpy>=1.18
Requires-Dist: matplotlib>=3.0
Requires-Dist: scipy>=1.5
Requires-Dist: pandas>=1.0
Requires-Dist: scikit-learn>=0.24
Requires-Dist: Pillow>=8.0
Requires-Dist: pytest>=6.0
Dynamic: author
Dynamic: author-email
Dynamic: classifier
Dynamic: description
Dynamic: description-content-type
Dynamic: home-page
Dynamic: requires-dist
Dynamic: requires-python
Dynamic: summary
